inboard/__init__.py
inboard/gunicorn_conf.py
inboard/gunicorn_workers.py
inboard/logging_conf.py
inboard/py.typed
inboard/start.py
inboard/types.py
inboard/app/__init__.py
inboard/app/main_base.py
inboard/app/main_fastapi.py
inboard/app/main_starlette.py
inboard/app/prestart.py
inboard/app/utilities_fastapi.py
inboard/app/utilities_starlette.py
inboard-0.86.0.dist-info/METADATA
inboard-0.86.0.dist-info/WHEEL
inboard-0.86.0.dist-info/licenses/LICENSE
inboard-0.86.0.dist-info/RECORD
