Metadata-Version: 2.4
Name: inboard
Version: 0.86.0
Summary: Docker images and utilities to power your Python APIs and help you ship faster.
Project-URL: Docker, https://github.com/br3ndonland/inboard/pkgs/container/inboard
Project-URL: Documentation, https://inboard.bws.bio
Project-URL: Homepage, https://github.com/br3ndonland/inboard
Project-URL: Repository, https://github.com/br3ndonland/inboard
Author-email: Brendon Smith <bws@bws.bio>
License-Expression: MIT
License-File: LICENSE
Keywords: asgi,docker,fastapi,gunicorn,uvicorn
Classifier: Framework :: FastAPI
Classifier: Natural Language :: English
Classifier: Programming Language :: Python :: 3
Classifier: Programming Language :: Python :: 3.10
Classifier: Programming Language :: Python :: 3.11
Classifier: Programming Language :: Python :: 3.12
Classifier: Programming Language :: Python :: 3.13
Classifier: Topic :: Internet :: Log Analysis
Classifier: Topic :: Internet :: WWW/HTTP :: HTTP Servers
Classifier: Topic :: Internet :: WWW/HTTP :: WSGI
Classifier: Topic :: Software Development :: Libraries :: Application Frameworks
Classifier: Topic :: System :: Software Distribution
Classifier: Topic :: Utilities
Classifier: Typing :: Typed
Requires-Python: <4,>=3.10
Requires-Dist: gunicorn==23.0.0
Requires-Dist: uvicorn==0.28.1
Provides-Extra: checks
Requires-Dist: basedpyright<1.38,>=1.37; extra == 'checks'
Requires-Dist: ruff<0.15,>=0.14; extra == 'checks'
Provides-Extra: docs
Requires-Dist: mkdocs-material<10,>=9; extra == 'docs'
Provides-Extra: fastapi
Requires-Dist: fastapi==0.128.0; extra == 'fastapi'
Provides-Extra: starlette
Requires-Dist: starlette<0.51.0,>=0.40.0; extra == 'starlette'
Provides-Extra: tests
Requires-Dist: coverage[toml]<8,>=7.10; extra == 'tests'
Requires-Dist: httpx<1,>=0.23; extra == 'tests'
Requires-Dist: pytest-mock<4,>=3; extra == 'tests'
Requires-Dist: pytest-timeout<3,>=2; extra == 'tests'
Requires-Dist: pytest<9,>=8.1.1; extra == 'tests'
Requires-Dist: trustme<2,>=1.2; extra == 'tests'
Provides-Extra: uvicorn-fast
Requires-Dist: httptools>=0.6.3; extra == 'uvicorn-fast'
Requires-Dist: uvloop>0.15.1; (sys_platform != 'win32' and (sys_platform != 'cygwin' and platform_python_implementation != 'PyPy')) and extra == 'uvicorn-fast'
Requires-Dist: websockets>=10.4; extra == 'uvicorn-fast'
Provides-Extra: uvicorn-standard
Requires-Dist: uvicorn[standard]==0.28.1; extra == 'uvicorn-standard'
